dell_printer_parser/__init__.py
dell_printer_parser/const.py
dell_printer_parser/printer_parser.py
dell_printer_parser/model/__init__.py
dell_printer_parser/model/events.py
dell_printer_parser/model/information.py
dell_printer_parser/model/print_volume.py
dell_printer_parser/model/status.py
dell_printer_parser-0.0.5.dist-info/LICENSE
dell_printer_parser-0.0.5.dist-info/METADATA
dell_printer_parser-0.0.5.dist-info/WHEEL
dell_printer_parser-0.0.5.dist-info/top_level.txt
dell_printer_parser-0.0.5.dist-info/RECORD
